{
  "la666150458": "East Gate Contact Sensor",
  "pb016222311": "PB01 Button",
  "lr-temp-humid-001": "North Twin Approach Sensor",
  "lr-temp-humid-002": "Baker View Turn Sensor",
  "la666053402": "Dailey Prairie Sensor",
  "la666053403": "South Twin Approach Sensor",
  "la666050494": "Dailey Prairie Ground Sensor",
  "la666054870": "North Twin West Ridge Sensor",
  "la666054877": "N Twin Extra Sensor",
  "lr-distance-sensor": "Snow Depth Sensor",
  "t65n6269142": "3D Printer Cabinet Sensor",
  "t65n6269147": "Sauna Sensor",
  "muon-air-sensor-001": "Olivine-Wx1 Sensor",
  "muon-air-sensor-002": "Olivine-Wx2 Sensor",
  "muon-air-sensor-003": "Olivine-Wx3 Sensor",
  "df-robot-001": "DFRobot SEN0466",
  "earthquake-rak-10703": "Earthquake Sensor",
  "6773a47722230004": "VS370 Occupancy Sensor",
  "9181010k6063240022": "RAK Weather Station 002"
}
